{
	"zones":
	[
		{"name": "1,1", "attributes": {"locationX": 1, "locationY": 1}, "cards": [], "type": "showEachCard", "visibleTo": ["X", "O"]},
		{"name": "1,2", "attributes": {"locationX": 1, "locationY": 2}, "cards": [], "type": "showEachCard", "visibleTo": ["X", "O"]},
		{"name": "1,3", "attributes": {"locationX": 1, "locationY": 3}, "cards": [], "type": "showEachCard", "visibleTo": ["X", "O"]},
		{"name": "2,1", "attributes": {"locationX": 2, "locationY": 1}, "cards": [], "type": "showEachCard", "visibleTo": ["X", "O"]},
		{"name": "2,2", "attributes": {"locationX": 2, "locationY": 2}, "cards": [], "type": "showEachCard", "visibleTo": ["X", "O"]},
		{"name": "2,3", "attributes": {"locationX": 2, "locationY": 3}, "cards": [], "type": "showEachCard", "visibleTo": ["X", "O"]},
		{"name": "3,1", "attributes": {"locationX": 3, "locationY": 1}, "cards": [], "type": "showEachCard", "visibleTo": ["X", "O"]},
		{"name": "3,2", "attributes": {"locationX": 3, "locationY": 2}, "cards": [], "type": "showEachCard", "visibleTo": ["X", "O"]},
		{"name": "3,3", "attributes": {"locationX": 3, "locationY": 3}, "cards": [], "type": "showEachCard", "visibleTo": ["X", "O"]},
		{"name": "X's Hand", "attributes": {}, "cards": [], "type": "showEachCard", "visibleTo": ["X"]},
		{"name": "O's Hand", "attributes": {}, "cards": [], "type": "showEachCard", "visibleTo": ["O"]}
	],
	"cardTypes":
	[
		{"name": "X", "attributes": {"value": "X"}, "actions": [{"templateName": "putInZone"}]},
		{"name": "O", "attributes": {"value": "O"}, "actions": [{"templateName": "putInZone"}]}
	],
	"actionTemplates":
	[
		{"name": "putInZone", "description": "Play card in a selected zone.", "result": "putInZoneResult", "checkLegality": "putInZoneCheckLegality", "inputTypes": ["zone"]}
	],
	"players":
	[
		{"name": "X", "zones": ["X's Hand"], "attributes": {}},
		{"name": "O", "zones": ["O's Hand"], "attributes": {}}
	],
	"init":
	[
		{"zoneName": "X's Hand", "cardNames": ["X", "X", "X", "X", "X"]},
		{"zoneName": "O's Hand", "cardNames": ["O", "O", "O", "O", "O"]},
		{"zonesPerLine": 3}
	],
	"functionFile": "newTTT.js",
	"winCondition": "newTTTWinCondition",
	"stateScore": "newTTTStateScore",
	"phases":
	[
		{"name": "placePiece", "init": "newTTTInitPhase", "endCondition": "newTTTPhaseEnd"}
	]
}